MANIFEST.in
README.md
build.py
requirements-dev.txt
requirements.txt
setup.py
looperator/__init__.py
looperator/handler.py
looperator/operation.py
looperator/operator.py
looperator/process.py
looperator/record.py
looperator/service.py
looperator/superator.py
looperator.egg-info/PKG-INFO
looperator.egg-info/SOURCES.txt
looperator.egg-info/dependency_links.txt
looperator.egg-info/requires.txt
looperator.egg-info/top_level.txt