Metadata-Version: 2.1
Name: looperator
Version: 1.9.0
Summary: A python module to easily run loop based operations, control the starting, stopping of the loop, and handle exceptions in real time.
Home-page: https://github.com/Shahaf-F-S/looperator
Author: Shahaf Frank-Shapir
Author-email: shahaffrs@gmail.com
License: MIT
Classifier: Intended Audience :: Developers
Classifier: License :: OSI Approved :: MIT License
Classifier: Programming Language :: Python
Classifier: Programming Language :: Python :: 3
Classifier: Programming Language :: Python :: 3.8
Classifier: Programming Language :: Python :: 3.9
Classifier: Programming Language :: Python :: 3.10
Classifier: Programming Language :: Python :: 3.11
Classifier: Operating System :: OS Independent
Provides-Extra: dev
